whl_hub/__init__.py
whl_hub/main.py
whl_hub/manager.py
whl_hub/map_operations.py
whl_hub/meta.py
whl_hub/model_operations.py
whl_hub/utils.py
whl_hub-0.0.1.dist-info/licenses/LICENSE
whl_hub-0.0.1.dist-info/METADATA
whl_hub-0.0.1.dist-info/WHEEL
whl_hub-0.0.1.dist-info/entry_points.txt
whl_hub-0.0.1.dist-info/top_level.txt
whl_hub-0.0.1.dist-info/RECORD
